<?xml version="1.0" encoding="utf-8" ?><dwsync><file name="404.html" server="gm.pswprinters.co.uk" local="3547634086" remote="3545212080" Dst="-1" /><file name="an.html" server="gm.pswprinters.co.uk" local="3547634086" remote="3545212080" Dst="-1" /><file name="apple-touch-icon-144x144-precomposed.png" server="gm.pswprinters.co.uk" local="3547634086" remote="3545212080" Dst="-1" /><file name="apple-touch-icon-114x114-precomposed.png" server="gm.pswprinters.co.uk" local="3547634086" remote="3545212080" Dst="-1" /><file name="apple-touch-icon-57x57-precomposed.png" server="gm.pswprinters.co.uk" local="3547634086" remote="3545212080" Dst="-1" /><file name="apple-touch-icon-72x72-precomposed.png" server="gm.pswprinters.co.uk" local="3547634087" remote="3545212080" Dst="-1" /><file name="apple-touch-icon.png" server="gm.pswprinters.co.uk" local="3547634087" remote="3545212080" Dst="-1" /><file name="apple-touch-icon-precomposed.png" server="gm.pswprinters.co.uk" local="3547634087" remote="3545212080" Dst="-1" /><file name="CHANGELOG.md" server="gm.pswprinters.co.uk" local="3547634087" remote="3545212080" Dst="-1" /><file name="CONTRIBUTING.md" server="gm.pswprinters.co.uk" local="3547634087" remote="3545212080" Dst="-1" /><file name="crossdomain.xml" server="gm.pswprinters.co.uk" local="3547634087" remote="3545212080" Dst="-1" /><file name="favicon.ico" server="gm.pswprinters.co.uk" local="3547634089" remote="3545212140" Dst="-1" /><file name="form.html" server="gm.pswprinters.co.uk" local="3547634089" remote="3545217900" Dst="-1" /><file name="headlines_style.css" server="gm.pswprinters.co.uk" local="3547634090" remote="3545212080" Dst="-1" /><file name="humans.txt" server="gm.pswprinters.co.uk" local="3547634090" remote="3545212140" Dst="-1" /><file name="index.html" server="gm.pswprinters.co.uk" local="3548176046" remote="3548176140" Dst="-1" /><file name="LICENSE.md" server="gm.pswprinters.co.uk" local="3547634097" remote="3545212140" Dst="-1" /><file name="README.md" server="gm.pswprinters.co.uk" local="3547634098" remote="3545212140" Dst="-1" /><file name="robots.txt" server="gm.pswprinters.co.uk" local="3547634098" remote="3545212140" Dst="-1" /><file name="send.php" server="gm.pswprinters.co.uk" local="3547634098" remote="3545217960" Dst="-1" /><file name="test.html" server="gm.pswprinters.co.uk" local="3547634101" remote="3545212140" Dst="-1" /></dwsync>